{"lastError":"","response":{"reportBase":{"caseNum":"105,家聲抗,1","caseType":"V","codeNum":"家聲抗","content":"臺灣臺北地方法院民事裁定　　　　　　105年度家聲抗字第1號\n抗　告　人　游榮盛\n代　理　人　高瑩律師\n複　代理人　陳逸融律師\n上列抗告人聲請改定監護人事件，對於中華民國104年11月27日\n本院104年度監宣字第228號裁定提起抗告，本院裁定如下：\n    主  文\n抗告駁回。\n抗告程序費用新臺幣壹仟元由抗告人負擔。\n    理  由\n一、按有事實足認監護人不符受監護人之最佳利益，或有顯不適\n    任之情事者，法院得依受監護人、四親等內之親屬、檢察官\n    、主管機關或其他利害關係人之聲請，改定適當之監護人，\n    不受民法第1094條第1項規定之限制，為民法第1106條之1第\n    1項定有明文，依同法第1113條規定，於成年人之監護人改\n    定應準用之。本件抗告人為受監護人游周銀之五子，其以監\n    護人游萬壽不適任及其執行監護人職務有損受監護人利益為\n    由，聲請改定監護人，自無不可，合先敘明。\n二、抗告人主張：受監護人游周銀因罹患失智症，前經本院以\n    102年度監宣字第591號裁定宣告監護，並選定其配偶游萬壽\n    為監護人，及指定其三子游榮柏為會同開具財產清冊之人，\n    惟上開程序未曾通知抗告人表示意見，且游萬壽嗣後利用其\n    為游周銀監護人之身分，主張抗告人名下新北市○○區○○\n    路000巷000號10樓房地係游周銀借名登記，對抗告人提起所\n    有權移轉登記訴訟，其濫訴行為有損害受監護人利益之虞，\n    顯已不適任監護人，原審未經踐行調查受監護人與其他關係\n    人間之生活及情感狀況，亦未敘明何以採納新北市及臺北市\n    政府社會局之訪視調查報告之評估建議，即遽以駁回抗告人\n    聲請，於法有違，爰提起本件抗告，求為廢棄原裁定云云。\n三、經查，本院102年度監宣字第591號裁定監護宣告時，依職權\n    選任受監護宣告人游周銀之配偶游萬壽為監護人，及指定其\n    三子游榮柏為會同開具財產清冊之人，其後游萬壽會同游榮\n    柏於民國103年10月31日共同陳報受監護宣告人游周銀之財\n    產清冊准予備查在案，有該案卷宗影本在卷可憑。又原審為\n    調查由游萬壽擔任監護人有無不符合受監護人之最佳利益或\n    顯不適任情事，除囑託新北市及臺北市政府社會局進行訪視\n    調查外，並通知受監護人之最近親屬即配偶游萬壽及四名兒\n    子游榮豊、游榮堯、游榮柏、游榮賢等人到庭陳述，查受監\n    護人游周銀生活無法自理，確有身上照護及財產管理之需要\n    ，監護人游萬壽雖年邁但頭腦清晰，家中大小事務均由其決\n    定，為掌控及主導角色，具監護意願及能力，其與受監護人\n    同住，並請外勞協助照顧，復有次子、三子及四子無條件支\n    持，整體支持系統良好，原審因認由其擔任監護人應屬適當\n    。本院審酌監護人游萬壽代理受監護人對抗告人訴請所有權\n    移轉登記，由形式觀之，係為受監護人主張財產上權利，尚\n    無不利益於受監護人之處，況抗告人於該訴訟已受敗訴判決\n    確定，業經本院依職權調閱臺灣新北地方法院103年度重訴\n    字第802號民事判決及臺灣高等法院民事判決104年度重上字\n    第830號民事判決附卷可憑，則抗告人應將該等房地所有權\n    移轉登記與受監護人，自不能認為監護人有何損害受監護人\n    之利益可言。原審駁回抗告人聲請，核無違誤，抗告意旨猶\n    執前詞指摘原裁定不當，聲明廢棄，為無理由，應予駁回。\n    爰裁定如主文。\n中    華    民    國  105    年    5    月    23    日\n                  家事法庭審判長法    官  <a href=\"https://www.pingluweb.com.tw/#!judgeDetail?id=50e3f66021129327c1d36f90\" target=\"_blank\">徐麗瑩</a>\n                                法    官  <a href=\"https://www.pingluweb.com.tw/#!judgeDetail?id=50e3f65e21129327c1d36f60\" target=\"_blank\">彭南元</a>\n                                法    官  <a href=\"https://www.pingluweb.com.tw/#!judgeDetail?id=556b7f9421129ab39fff6901\" target=\"_blank\">黃怡菁</a>\n以上正本係照原本作成。\n如不服本裁定，僅得於收受本裁定正本送達後10日內，以適用法\n規顯有錯誤為理由並委任律師為代理人，向本院提出再抗告狀。\n中    華    民    國   105    年    5     月    26    日\n                                書記官  張妤瑄\n","courtCode":"TPD","fulltext":null,"gist":null,"identifier":"TPDV,105,家聲抗,1,20160523,1-63d043f9-cc39-49a8-8f39-2b4b1bef1cf6","issue":"改定監護人","jno":"1","jtype":"R","judgeDate":1463932800000,"jyear":105,"lastUpdate":1594574280979,"reportStatus":7,"source":"opendata","summary":null},"report":{"amount":0,"appellant":null,"appellantAgent":null,"appellantLawyer":null,"appellee":null,"appelleeAgent":null,"appelleeLawyer":null,"assignCounsel":null,"beJudgedPerson":null,"caseNum":["105,家聲抗,1"],"caseType":"V","chosenCounsel":null,"clerk":"張妤瑄","codeNum":"家聲抗","courtCode":"TPD","defendant":null,"defendantAgent":null,"defendantLawyer":null,"flag":false,"identifier":"TPDV,105,家聲抗,1,20160523,1-63d043f9-cc39-49a8-8f39-2b4b1bef1cf6","inmate":null,"interlocutoryPetitioner":null,"jno":"1","jtype":"R","judge":"黃怡菁","judgeDate":1463932800000,"jyear":105,"lastUpdate":1594574280977,"lawyerCustomers":null,"level":1,"lose":null,"main":"抗告駁回。\n抗告程序費用新臺幣壹仟元由抗告人負擔。","money":0,"petitioner":null,"petitionerAgent":null,"petitionerLawyer":null,"plaintiff":null,"plaintiffAgent":null,"plaintiffLawyer":null,"presideJudge":"徐麗瑩","previousCaseNum":"104,監宣,228","previousCourtCode":"TPD","previousJudgeDate":1448553600000,"privateProsecutor":null,"proportion":0.0,"prosecutor":null,"publicDefender":null,"publicJudge":null,"puisne":["彭南元"],"respondent":null,"result":2,"sentence":null,"statute":["民法第1106條之1第1項","民法第1113條","民法第1094條第1項"],"tags":null,"type":"民事裁定","win":null},"statute":[{"items":[{"cnum":"第一千零九十四條第一項","num":"第1094條第1項","val":1094},{"cnum":"第一千一百零六條之一第一項","num":"第1106條之1第1項","val":1106},{"cnum":"第一千一百十三條","num":"第1113條","val":1113}],"statute":"民法"}],"tags":null},"success":true}