{"lastError":"","response":{"reportBase":{"caseNum":"107,監宣,296","caseType":"V","codeNum":"監宣","content":"臺灣桃園地方法院民事裁定　　　　　　107年度監宣字第296號\n聲　請　人　桃園市政府社會局\n法定代理人　古梓龍\n相　對　人　林春菊\n關　係　人　桃園市政府\n法定代理人　鄭文燦\n上列聲請人聲請改定監護人事件，本院裁定如下：\n    主    文\n改定桃園市政府社會局為受監護宣告之人林春菊（女、民國00年\n0 月00日生）之監護人。\n指定桃園市政府為會同開具財產清冊之人。\n聲請程序費用由受監護宣告之人林春菊負擔。\n    理    由\n一、有事實足認監護人不符受監護人之最佳利益，或有顯不適任\n    之情事者，法院得依前條第1 項聲請權人之聲請，改定適當\n    之監護人，不受第1094條第1 項規定之限制；法院依前項選\n    定監護人或依第1106條及第1106條之1 另行選定或改定監護\n    人時，應同時指定會同開具財產清冊之人，民法第1106條之\n    1 第1 項、第1094條第4 項明文規定。另依民法第1113條，\n    前開規定於成年人之監護準用之。\n二、本件聲請意旨略以：相對人前經本院以民國104 年11月30日\n    104 年度監宣字第196 號裁定宣告為受監護宣告人，並選任\n    相對人之女兒林月琴為監護人，然聲請人於106 年4 月27日\n    協助相對人安置於永康護理之家後，林月琴皆未曾前往探視\n    。相對人後續照顧事宜，乃經聲請人協助安排，然林月琴長\n    期失聯，導致相對人未能轉換為長期穩定安置身份，形同將\n    相對人遺棄於機構內，足見林月琴無法適任相對人之監護人\n    ，為維護相對人之最佳利益，應有改定監護人之必要，爰依\n    民法第1113條準用民法第1106條之1 第1 款規定，聲請改由\n    聲請人擔任相對人之監護人，併指定關係人桃園市政府為會\n    同開具財產清冊之人等語。\n三、經查，本件聲請，業據聲請人提出戶籍謄本、本院104 年度\n    監宣字第196 號裁定及確定證明書、桃園市政府社會局函等\n    件為證，並經本院依職權調閱104 年度監宣字第196 號卷宗\n    核閱無訛，堪信為真實。另經本院依職權調取林月琴之入出\n    境資訊連結作業、臺灣高等法院在監在押全國紀綠表、通緝\n    記錄表，林月琴無出境、在監在押、通緝之紀錄，而本院於\n    107 年5 月27日函請林月琴於文到7 日內具狀到院，對本件\n    聲請表示意見，該函於107 年5 月30日寄存送達，然林月琴\n    迄今均未具狀等情，有本院送達證書在卷可佐。本院認林月\n    琴已無從聯繫，不知所蹤，顯不適任，為相對人之最佳利益\n    ，自有改定監護人之必要。\n四、再按法院選定監護人時，應依受監護宣告之人之最佳利益，\n    優先考量受監護宣告之人之意見，審酌一切情狀，並注意下\n    列事項：（一）受監護宣告之人之身心狀態與生活及財產狀\n    況。（二）受監護宣告之人與其配偶、子女或其他共同生活\n    之人間之情感狀況。（三）監護人之職業、經歷、意見及其\n    與受監護宣告之人之利害關係。（四）法人為監護人時，其\n    事業之種類與內容，法人及其代表人與受監護宣告之人之利\n    害關係，民法第1111條之1 定有明文。\n五、本院審酌聲請人為相對人住所地之社政主管機關，擁有一定\n    之人力、財力等資源，由聲請人擔任監護人，應合乎相對人\n    之最佳利益；另關係人桃園市政府具備人力、財力等資源可\n    負責桃園市民之社會行政等事項，就相對人之財產狀況亦有\n    權利進行相當之了解，並有能力保護其財產之管理，由關係\n    人桃園市政府擔任會同開具財產清冊之人，應屬適宜，爰依\n    前揭規定改定聲請人為相對人之監護人、桃園市政府指定關\n    係人擔任會同開具財產清冊之人。又依民法第1113條準用同\n    法第1099條之規定，於監護開始時，監護人對於受監護宣告\n    人之財產，應會同開具財產清冊之人於2 個月內開具財產清\n    冊並陳報法院，併此敘明。\n六、依家事事件法第164 條第2 項，裁定如主文。\n中    華    民    國    107   年     8    月    28    日\n                  家事法庭  法  官  <a href=\"https://www.pingluweb.com.tw/#!judgeDetail?id=50e3f65d21129327c1d36e56\" target=\"_blank\">孫健智</a>\n以上正本係照原本作成。\n如對本裁定抗告須於裁定送達後10日內向本院提出抗告狀。\n中    華    民    國   107    年    8     月    28    日\n                            書記官  劉家慶\n","courtCode":"TYD","fulltext":null,"gist":null,"identifier":"TYDV,107,監宣,296,20180828,1-c87f1cf1-6f64-484e-898b-15897ed1cf5f","issue":"改定監護人","jno":"296","jtype":"R","judgeDate":1535385600000,"jyear":107,"lastUpdate":1594595985394,"reportStatus":7,"source":"opendata","summary":null},"report":{"amount":0,"appellant":null,"appellantAgent":null,"appellantLawyer":null,"appellee":null,"appelleeAgent":null,"appelleeLawyer":null,"assignCounsel":null,"beJudgedPerson":null,"caseNum":["107,監宣,296"],"caseType":"V","chosenCounsel":null,"clerk":"劉家慶","codeNum":"監宣","courtCode":"TYD","defendant":null,"defendantAgent":null,"defendantLawyer":null,"flag":false,"identifier":"TYDV,107,監宣,296,20180828,1-c87f1cf1-6f64-484e-898b-15897ed1cf5f","inmate":null,"interlocutoryPetitioner":null,"jno":"296","jtype":"R","judge":null,"judgeDate":1535385600000,"jyear":107,"lastUpdate":1594595985334,"lawyerCustomers":null,"level":1,"lose":null,"main":"改定桃園市政府社會局為受監護宣告之人林春菊（女、民國00年\n0 月00日生）之監護人。\n指定桃園市政府為會同開具財產清冊之人。\n聲請程序費用由受監護宣告之人林春菊負擔。","money":0,"petitioner":["桃園市政府社會局"],"petitionerAgent":null,"petitionerLawyer":null,"plaintiff":null,"plaintiffAgent":null,"plaintiffLawyer":null,"presideJudge":"孫健智","previousCaseNum":null,"previousCourtCode":null,"previousJudgeDate":null,"privateProsecutor":null,"proportion":0.0,"prosecutor":null,"publicDefender":null,"publicJudge":null,"puisne":null,"respondent":null,"result":0,"sentence":null,"statute":["民法第1111條之1","民法第1106條之1第1項","民法第1099條","民法第1113條","民法第1094條第4項","民法第1106條之1第1款"],"tags":null,"type":"民事裁定","win":null},"statute":[{"items":[{"cnum":"第一千零九十四條第四項","num":"第1094條第4項","val":1094},{"cnum":"第一千零九十九條","num":"第1099條","val":1099},{"cnum":"第一千一百零六條之一第一項","num":"第1106條之1第1項","val":1106},{"cnum":"第一千一百零六條之一第一款","num":"第1106條之1第1款","val":1106},{"cnum":"第一千一百十一條之一","num":"第1111條之1","val":1111},{"cnum":"第一千一百十三條","num":"第1113條","val":1113}],"statute":"民法"}],"tags":null},"success":true}